{"assets/images/Ellipse 2.png":["assets/images/Ellipse 2.png"],"assets/images/Vector 1.png":["assets/images/Vector 1.png"],"assets/images/bG3.png":["assets/images/bG3.png"],"assets/images/bg1.png":["assets/images/bg1.png"],"assets/images/bg2.png":["assets/images/bg2.png"],"assets/images/ellipse (1).png":["assets/images/ellipse (1).png"],"assets/images/grl.png":["assets/images/grl.png"],"assets/images/s1.png":["assets/images/s1.png"],"assets/images/shaan.png":["assets/images/shaan.png"],"assets/images/star.png":["assets/images/star.png"],"packages/cupertino_icons/assets/CupertinoIcons.ttf":["packages/cupertino_icons/assets/CupertinoIcons.ttf"]}